{
  "runId": "c0f5042b-ca88-4c33-9ff8-275eb8b84e71",
  "status": "InProgress",
  "mode": "Delta",
  "dryRun": true,
  "stage": "ProcessingWorkers",
  "startedAt": "2026-03-22T22:29:30.6917160-04:00",
  "lastUpdatedAt": "2026-03-22T22:37:30.6945620-04:00",
  "completedAt": "",
  "currentWorkerId": "100003",
  "lastAction": "Evaluating worker 100003.",
  "processedWorkers": 67,
  "totalWorkers": 250,
  "creates": 0,
  "updates": 1,
  "enables": 0,
  "disables": 0,
  "graveyardMoves": 0,
  "deletions": 0,
  "quarantined": 0,
  "conflicts": 0,
  "guardrailFailures": 0,
  "manualReview": 1,
  "unchanged": 0,
  "errorMessage": "",
  "runtimeStatusPath": "/Users/chrisbrien/dev/github.com/syncfactors/./reports/demo/state/runtime-status.json"
}
